{"items": {"3": {"points": {}, "date": "2019-02-14", "label": "004", "linksto": {"psoo": [], "days": [], "props": ["36"]}}, "14": {"points": {}, "date": "2019-03-01", "label": "015", "linksto": {"psoo": [], "days": [], "props": ["45"]}}, "18": {"points": {}, "date": "2019-03-07", "label": "019", "linksto": {"psoo": ["19", "20"], "days": [], "props": ["48"]}}, "2": {"points": {}, "date": "2019-02-13", "label": "003", "linksto": {"psoo": ["13"], "days": [], "props": ["35"]}}, "13": {"points": {}, "date": "2019-02-28", "label": "014", "linksto": {"psoo": [], "days": [], "props": ["44"]}}, "12": {"points": {}, "date": "2019-02-27", "label": "013", "linksto": {"psoo": ["18"], "days": [], "props": ["43"]}}, "11": {"points": {}, "date": "2019-02-26", "label": "012", "linksto": {"psoo": [], "days": [], "props": ["42"]}}, "6": {"points": {}, "date": "2019-02-19", "label": "007", "linksto": {"psoo": [], "days": [], "props": ["38"]}}, "16": {"points": {}, "date": "2019-03-05", "label": "017", "linksto": {"psoo": [], "days": [], "props": ["46"]}}, "15": {"points": {}, "date": "2019-03-04", "label": "016", "linksto": {"psoo": [], "days": [], "props": []}}, "8": {"points": {}, "date": "2019-02-22", "label": "009", "linksto": {"psoo": ["14", "15", "16"], "days": [], "props": ["40"]}}, "17": {"points": {}, "date": "2019-03-06", "label": "018", "linksto": {"psoo": [], "days": [], "props": ["47"]}}, "10": {"points": {}, "date": "2019-02-25", "label": "011", "linksto": {"psoo": [], "days": [], "props": ["41"]}}, "9": {"points": {}, "date": "2019-02-23", "label": "010", "linksto": {"psoo": ["17"], "days": [], "props": []}}, "4": {"points": {}, "date": "2019-02-15", "label": "005", "linksto": {"psoo": [], "days": [], "props": []}}, "7": {"points": {}, "date": "2019-02-20", "label": "008", "linksto": {"psoo": [], "days": [], "props": ["39"]}}, "5": {"points": {}, "date": "2019-02-18", "label": "006", "linksto": {"psoo": [], "days": [], "props": ["37"]}}, "0": {"points": {}, "date": "2019-02-11", "label": "001", "linksto": {"psoo": ["0", "1", "2", "3", "4", "5", "6", "7"], "days": [], "props": ["33"]}}, "1": {"points": {}, "date": "2019-02-12", "label": "002", "linksto": {"psoo": ["8", "9", "10", "11", "12"], "days": [], "props": ["34"]}}}, "date": "2019-03-08", "author": "Ben"}