{"items": {"1": {"points": {}, "linksto": {"props": ["34"], "psoo": ["8", "9", "10", "11", "12"], "days": []}, "label": "002", "date": "2019-02-12"}, "2": {"points": {}, "linksto": {"props": ["35"], "psoo": ["13"], "days": []}, "label": "003", "date": "2019-02-13"}, "4": {"points": {}, "linksto": {"props": [], "psoo": [], "days": []}, "label": "005", "date": "2019-02-15"}, "0": {"points": {}, "linksto": {"props": ["33"], "psoo": ["0", "1", "2", "3", "4", "5", "6", "7"], "days": []}, "label": "001", "date": "2019-02-11"}, "3": {"points": {}, "linksto": {"props": ["36"], "psoo": [], "days": []}, "label": "004", "date": "2019-02-14"}}, "author": "Ben", "date": "2019-02-16"}